pyexcel_libxlsxw/__init__.py
pyexcel_libxlsxw/xlsxw.py
pyexcel_libxlsxw-0.6.0.dist-info/LICENSE
pyexcel_libxlsxw-0.6.0.dist-info/METADATA
pyexcel_libxlsxw-0.6.0.dist-info/WHEEL
pyexcel_libxlsxw-0.6.0.dist-info/top_level.txt
pyexcel_libxlsxw-0.6.0.dist-info/RECORD
