Metadata-Version: 2.1
Name: pyexcel-libxlsxw
Version: 0.6.0
Summary: A wrapper library of libxlsxwpy to write data in xlsx and xlsm format
Home-page: https://github.com/pyexcel/pyexcel-libxlsxw
Author: chfw
Author-email: info@pyexcel.org
License: New BSD
Download-URL: https://github.com/pyexcel/pyexcel-libxlsxw/archive/0.6.0.tar.gz
Keywords: python,xlsx
Platform: UNKNOWN
Classifier: Topic :: Software Development :: Libraries
Classifier: Programming Language :: Python
Classifier: Intended Audience :: Developers
Classifier: Programming Language :: Python :: 3 :: Only
Classifier: Programming Language :: Python :: 3.6
Classifier: Programming Language :: Python :: 3.7
Classifier: Programming Language :: Python :: 3.8
Classifier: Development Status :: 3 - Alpha
Classifier: Programming Language :: Python :: Implementation :: PyPy
Requires-Python: >=3.6
Requires-Dist: libxlsxwpy
Requires-Dist: pyexcel-io (>=0.6.2)
